remote_events-0.2.61.dist-info/licenses/LICENSE
remote_functions/RemoteFunctions.py
remote_functions/__init__.py
remote_events-0.2.61.dist-info/METADATA
remote_events-0.2.61.dist-info/WHEEL
remote_events-0.2.61.dist-info/top_level.txt
remote_events-0.2.61.dist-info/RECORD
