Metadata-Version: 2.4
Name: remote_events
Version: 0.2.61
Summary: Connor's Remote Events (RE) is a simple library that allows the end-user to call python functions from another server.
Author-email: Connor White <connor.sw.personal@gmail.com>
License-Expression: MIT
Project-URL: Homepage, https://github.com/CorniiDog/remote_events
Project-URL: Issues, https://github.com/CorniiDog/remote_events/issues
Classifier: Programming Language :: Python :: 3
Classifier: Operating System :: OS Independent
Requires-Python: >=3.9
License-File: LICENSE
Requires-Dist: flask
Requires-Dist: requests
Requires-Dist: process-managerial
Requires-Dist: dill
Dynamic: license-file
